nuthon/__init__.py
nuthon/__main__.py
nuthon/abstract.py
nuthon/common.py
nuthon/ext.py
nuthon/folder.py
nuthon/json.py
nuthon/meta.py
nuthon/py.py
nuthon/resource.py
nuthon/run.py
nuthon/shard.py
nuthon/startup.py
nuthon/sync.py
nuthon/tag.py
nuthon/yl.py
nuthon/Entity/__init__.py
nuthon/Entity/__main__.py
nuthon/Entity/active_context.py
nuthon/Speaker/interactive.py
nuthon/kathon/__main__.py
nuthon-0.0.1.dist-info/LICENSE
nuthon-0.0.1.dist-info/METADATA
nuthon-0.0.1.dist-info/WHEEL
nuthon-0.0.1.dist-info/top_level.txt
nuthon-0.0.1.dist-info/RECORD
