Metadata-Version: 2.2
Name: nuthon
Version: 0.0.1
Summary: Python filesystem abstraction and experimentation with concurence.
Author-email: Sacha Carle <carle.sacha@gmail.com>
License: MIT License
Project-URL: Homepage, https://github.com/SachaCarle/python_distribution
Project-URL: Issues, https://github.com/SachaCarle/python_distribution/issues
Classifier: Programming Language :: Python :: 3
Classifier: Operating System :: OS Independent
Classifier: License :: OSI Approved :: MIT License
Requires-Python: >=3.7
License-File: LICENSE
